MANIFEST.in
README.md
setup.py
trex/__init__.py
trex/conf/__init__.py
trex/conf/lib_conf.py
trex/utils/__init__.py
trex/utils/log_util.py
trex/utils/security_util.py
trex/utils/string_util.py
trex/utils/url_util.py
trex/utils/common/__init__.py
trex/utils/common/cache_util.py
trex/utils/common/common_util.py
trex/utils/common/conftest.py
trex/utils/common/date_util.py
trex/utils/common/float_util.py
trex/utils/common/user_util.py
trex/utils/mail/__init__.py
trex/utils/mail/flask_mail_util.py
trex/utils/mail/mailjet_service_util.py
trex/utils/mail/mailjet_util.py
trex/utils/mail/sendgrid_util.py
trexcore.egg-info/PKG-INFO
trexcore.egg-info/SOURCES.txt
trexcore.egg-info/dependency_links.txt
trexcore.egg-info/requires.txt
trexcore.egg-info/top_level.txt