Metadata-Version: 2.1
Name: trexcore
Version: 0.1
Summary: TRex Core library package
Home-page: https://bitbucket.org/lokjac/trexcore
Author: Jack Lok
Author-email: sglok77@gmail.com
License: UNKNOWN
Platform: UNKNOWN
Classifier: Programming Language :: Python :: 3
Classifier: License :: OSI Approved :: MIT License
Classifier: Operating System :: OS Independent
